{
  "name": "UCO Bank - Daman",
  "address": "\nNo 1, Ganga appartment, mashal chowk road, Opp Sai Krupa society, Nani Daman, Daman, Dadra and Nagar Haveli and Daman and Diu 396210",
  "rating": "4.7 stars",
  "pincode": "396210",
  "reviews": [
    {
      "reviewer": "Aarti Saini",
      "rating": "5 stars",
      "date": "a year ago",
      "text": "One of the best banks in Daman. Whether you talk about their cooperative staff or the efficiency of their work, you'll always be delighted. I personally felt much appreciated and satisfied with their cooperation and way of handling customer. Thank you for your service UCO bank.🌄🌼 …",
      "bank_response": "No response from bank"
    },
    {
      "reviewer": "Nishant Choudhary",
      "rating": "5 stars",
      "date": "a year ago",
      "text": "Staff is cooperative, branch is neat. One of the best banks in Daman. I got my savings account opened in 5 minutes with tab banking.",
      "bank_response": "No response from bank"
    },
    {
      "reviewer": "Kirti Singh",
      "rating": "5 stars",
      "date": "2 years ago",
      "text": "Great and very quick service. Employees are very helpful, they listen to your queries and provides best solutions. Really positive environment is there in the bank.",
      "bank_response": "No response from bank"
    },
    {
      "reviewer": "Akshay Patel",
      "rating": "5 stars",
      "date": "2 years ago",
      "text": "Best service, Behaviour of every employee is so nice nd so helpful. You won't face any problems that u face in sbi bob etc, nd you will get all the benefits of the government bank.",
      "bank_response": "No response from bank"
    },
    {
      "reviewer": "ABHIMANYU CHAUHAN",
      "rating": "5 stars",
      "date": "2 years ago",
      "text": "One of oldest bank in daman with excellent customer service, each and every staff is very cordial.",
      "bank_response": "No response from bank"
    },
    {
      "reviewer": "Ankit Gupta",
      "rating": "5 stars",
      "date": "7 months ago",
      "text": "Very Good Staff",
      "bank_response": "No response from bank"
    },
    {
      "reviewer": "MIKESH KISHORKUMAR PARMAR",
      "rating": "1 star",
      "date": "3 years ago",
      "text": "Don't visit this bank because \"waste of time\" & no service",
      "bank_response": "No response from bank"
    },
    {
      "reviewer": "Anwar Ali",
      "rating": "5 stars",
      "date": "a year ago",
      "text": "Nice restaurants and supar service",
      "bank_response": "No response from bank"
    },
    {
      "reviewer": "Rajnish kumar",
      "rating": "5 stars",
      "date": "3 years ago",
      "text": "Excellent customer service..",
      "bank_response": "No response from bank"
    },
    {
      "reviewer": "Prashant Kumar Singh",
      "rating": "5 stars",
      "date": "2 years ago",
      "text": "Excellent service .",
      "bank_response": "No response from bank"
    },
    {
      "reviewer": "Pradeep Akarniya",
      "rating": "5 stars",
      "date": "3 years ago",
      "text": "Great service.",
      "bank_response": "No response from bank"
    },
    {
      "reviewer": "Rony",
      "rating": "4 stars",
      "date": "2 years ago",
      "text": "Good service",
      "bank_response": "No response from bank"
    },
    {
      "reviewer": "Babalu sahu",
      "rating": "5 stars",
      "date": "3 months ago",
      "text": "Khata number transfer Singrauli jila",
      "bank_response": "No response from bank"
    },
    {
      "reviewer": "nisha singh",
      "rating": "5 stars",
      "date": "3 years ago",
      "text": "No review text found",
      "bank_response": "No response from bank"
    },
    {
      "reviewer": "Dhiraj Singh",
      "rating": "5 stars",
      "date": "3 years ago",
      "text": "No review text found",
      "bank_response": "No response from bank"
    }
  ],
  "url": "https://www.google.com/maps/place/UCO+Bank+-+Daman/data=!4m7!3m6!1s0x3be0d13af579b621:0xe05b9172f4f950ac!8m2!3d20.4205893!4d72.8394985!16s%2Fg%2F11r_sh_1nc!19sChIJIbZ59TrR4DsRrFD59HKRW-A?authuser=0&hl=en&rclk=1",
  "source_file": "uco_bank_dadra_and_nagar_haveli_and_daman_and_diu.json"
}